pytest_gitlab_code_quality/__init__.py
pytest_gitlab_code_quality/plugin.py
pytest_gitlab_code_quality/recorder.py
pytest_gitlab_code_quality/report.py
pytest_gitlab_code_quality-0.2.1.dist-info/METADATA
pytest_gitlab_code_quality-0.2.1.dist-info/WHEEL
pytest_gitlab_code_quality-0.2.1.dist-info/entry_points.txt
pytest_gitlab_code_quality-0.2.1.dist-info/RECORD
