Metadata-Version: 2.3
Name: pytest-gitlab-code-quality
Version: 0.2.1
Summary: Collects warnings while testing and generates a GitLab Code Quality Report.
Project-URL: Homepage, https://github.com/NiclasvanEyk/pytest-gitlab-code-quality
Project-URL: Issues, https://github.com/NiclasvanEyk/pytest-gitlab-code-quality/issues
Project-URL: Changelog, https://github.com/NiclasvanEyk/pytest-gitlab-code-quality/blob/main/CHANGELOG.md
Author-email: Niclas van Eyk <niclas.eyk@gmail.com>
Classifier: Framework :: Pytest
Requires-Python: >=3.9
Requires-Dist: pytest>=8.1.1
